LICENSE
MANIFEST.in
README.rst
requirements.txt
setup.py
atlabs/__init__.py
atlabs/airtime.py
atlabs/config.py
atlabs/sms.py
atlabs/token.py
atlabs/voice.py
atlabs/tests/__init__.py
atlabs/tests/common.py
atlabs/tests/test_module.py
atlabs/utils/__init__.py
atlabs/utils/constants.py
atlabs/utils/error_handler.py
atlabs/utils/request_handler.py
atlabs/utils/response_handler.py
innovation_sandbox.egg-info/PKG-INFO
innovation_sandbox.egg-info/SOURCES.txt
innovation_sandbox.egg-info/dependency_links.txt
innovation_sandbox.egg-info/requires.txt
innovation_sandbox.egg-info/top_level.txt
nibss/Nibss.py
nibss/README.rst
nibss/__init__.py
nibss/bvnr.py
nibss/fingerprint.py
nibss/records.py
nibss/tests/__init__.py
nibss/tests/common.py
nibss/tests/test_module.py
nibss/utils/__init__.py
nibss/utils/calls.py
nibss/utils/crypt.py
nibss/utils/error_handler.py
sterling/README.rst
sterling/Sterling.py
sterling/__init__.py
sterling/account.py
sterling/transfer.py
sterling/tests/__init__.py
sterling/tests/common.py
sterling/tests/test_sterling.py
sterling/utils/__init__.py
sterling/utils/calls.py
sterling/utils/response_handler.py
union/__init__.py
union/config.py
union/enquiry.py
union/token.py
union/user.py
union/tests/__init__.py
union/tests/common.py
union/tests/test_module.py
url/__init__.py
url/base.py